cg_jupyter_mux/__init__.py
cg_jupyter_mux/config.py
cg_jupyter_mux/kernel_manager.py
cg_jupyter_mux/main.py
cg_jupyter_mux/message_handler.py
cg_jupyter_mux-0.2.2.dist-info/METADATA
cg_jupyter_mux-0.2.2.dist-info/WHEEL
cg_jupyter_mux-0.2.2.dist-info/entry_points.txt
cg_jupyter_mux-0.2.2.dist-info/RECORD
