Metadata-Version: 2.4
Name: cg-jupyter-mux
Version: 0.2.2
Summary: A multiplexer for the Jupyter kernel protocol using JSON Lines (JSONL) over stdin/stdout.
Author-email: CodeGrade <info@codegrade.com>
License-Expression: MIT
Keywords: asyncio,codegrade,jsonl,jupyter,jupyter-client,kernel,multiplexer,mux,protocol
Classifier: Development Status :: 3 - Alpha
Classifier: Environment :: Console
Classifier: Framework :: Jupyter
Classifier: Intended Audience :: Developers
Classifier: License :: OSI Approved :: MIT License
Classifier: Operating System :: OS Independent
Classifier: Programming Language :: Python :: 3
Classifier: Programming Language :: Python :: 3.10
Classifier: Programming Language :: Python :: 3.11
Classifier: Programming Language :: Python :: 3.12
Classifier: Topic :: Software Development :: Libraries :: Python Modules
Classifier: Topic :: System :: Networking
Classifier: Typing :: Typed
Requires-Python: ~=3.10
Requires-Dist: jupyter-client~=8.0
